{
  "elements": [
    "Death"
  ],
  "actions": [
    {
      "abilityName": "Cobolt",
      "abilityText": "If the enemy monster is <div><b>weak</b> [WEAK]</div> to this attack's element, this attack gains +2[ATK].</div>~EFFECTIVE~",
      "element": "Death",
      "statusFlg": false,
      "attack": 2,
      "speed": 1,
      "draw": 1,
      "discard": 0,
      "buff": 2,
      "lastUpdated": "Thu, 26 Jan 2023 17:57:55 GMT"
    },
    {
      "abilityName": "Static Void",
      "abilityText": "If the enemy monster is <div><b>weak</b> [WEAK]</div> to this attack's element, this attack gains +2[ATK].</div>~EFFECTIVE~",
      "element": "Electric",
      "statusFlg": false,
      "attack": 2,
      "speed": 5,
      "draw": 0,
      "discard": 0,
      "buff": 0,
      "lastUpdated": "Thu, 26 Jan 2023 17:57:55 GMT"
    },
    {
      "abilityName": "Arraydicate",
      "abilityText": "<b>Crush 2 [PQ]</b>~CRUSH~",
      "element": "Electric",
      "statusFlg": false,
      "attack": 3,
      "speed": 3,
      "draw": 0,
      "discard": 1,
      "buff": 2,
      "lastUpdated": "Thu, 26 Jan 2023 18:06:11 GMT"
    },
    {
      "abilityName": "Exception Caught",
      "abilityText": "<b>Single use.</b><br><br>Your opponent [-] [-] [-].~SINGLE~",
      "element": "Death",
      "statusFlg": false,
      "attack": 1,
      "speed": 9,
      "draw": 0,
      "discard": 2,
      "buff": 2,
      "lastUpdated": "Thu, 26 Jan 2023 18:06:11 GMT"
    }
  ],
  "buffs": [
    {
      "buffName": "Power Hotfix",
      "buffText": "If the enemy monster switched this turn, this monster gains {\"stat\": \"ATK\", \"num\": 3, \"isPositive\": true}.",
      "lastUpdated": "Thu, 26 Jan 2023 17:57:55 GMT"
    },
    {
      "buffName": "Protection Hotfix",
      "buffText": "If the enemy monster switched this turn, this monster gains {\"stat\": \"DEF\", \"num\": 3, \"isPositive\": true}.",
      "lastUpdated": "Thu, 26 Jan 2023 17:57:55 GMT"
    },
    {
      "buffName": "Refactor",
      "buffText": "<b>Super [B] [B]. </b><br><br>Attack speeds are reversed this turn and you win all speed ties.~SUPER~",
      "lastUpdated": "Thu, 15 Jul 2021 08:25:53 GMT"
    },
    {
      "buffName": "Download",
      "buffText": "When an enemy monster switches in, that monster loses 1[HP] and discard this aura.<br><br>When this card is discarded from duration, next turn your opponent must reveal their action before you select yours. ~AURA~",
      "auraDuration": 4,
      "lastUpdated": "Thu, 26 Jan 2023 18:06:11 GMT"
    }
  ],
  "monsterId": 10,
  "monsterName": "Phantomaton",
  "abilityText": "Whenever an enemy monsters performs a switch action, this monster heals 2[HP]. ~SWITCH~",
  "hp": 9,
  "promiseDescription": "Strike fear in your opponent when <b>Phantomaton</b> switches in to an advantageous matchup! Watch the enemy monster squirm when the cost of switching out is too high.",
  "initiative": 55,
  "imageFlg": true,
  "lastUpdated": "Thu, 26 Jan 2023 18:07:17 GMT"
}